<?xml version="1.0" encoding="gb2312"?>
<others>
    <Category name="TFController">
        <item name="zk">
            <server>10.9.236.165:2181,10.9.236.166:2181,10.9.236.167:2181</server>
            <timeout>1000</timeout>
            <FullPath>/TF/open/</FullPath>
        </item>

        <item name="TFMod">
            <!-- 以TFCODE为标签区分不同进程的MOD值,先读取环境变量TFCODE,得不到这从这里取对应TFCODE的标签值，得不到则取default值 -->
            <!-- default必须存在 -->
            <default>10</default>
        </item>
    </Category>

</others>